uuoskit/ABI.py
uuoskit/__init__.py
uuoskit/_uuoskit.cpython-39-darwin.so
uuoskit/block_log.py
uuoskit/chainapi.py
uuoskit/chainapi_async.py
uuoskit/chainapi_sync.py
uuoskit/chaincache.py
uuoskit/chainnative.py
uuoskit/common.py
uuoskit/compiler.py
uuoskit/config.py
uuoskit/crypto.py
uuoskit/defaultabi.py
uuoskit/exceptions.py
uuoskit/google_docstring.py
uuoskit/http_client.py
uuoskit/log.py
uuoskit/rpc_interface.py
uuoskit/test_helper.py
uuoskit/testnet.py
uuoskit/transaction.py
uuoskit/utils.py
uuoskit/wallet.py
uuoskit/wasmcompiler.py
uuoskit/contracts/eosio.bios/eosio.bios.abi
uuoskit/contracts/eosio.bios/eosio.bios.wasm
uuoskit/contracts/eosio.msig/eosio.msig.abi
uuoskit/contracts/eosio.msig/eosio.msig.wasm
uuoskit/contracts/eosio.system/eosio.system.abi
uuoskit/contracts/eosio.system/eosio.system.wasm
uuoskit/contracts/eosio.token/eosio.token.abi
uuoskit/contracts/eosio.token/eosio.token.wasm
uuoskit/contracts/eosio.wrap/eosio.wrap.abi
uuoskit/contracts/eosio.wrap/eosio.wrap.wasm
uuoskit/contracts/micropython/micropython.abi
uuoskit/contracts/micropython/micropython.wasm
uuoskit/contracts/micropython/micropython_eosio.wasm
uuoskit/data/eosio.system_eosio.abi
uuoskit/data/eosio.system_uuos.abi
uuoskit/data/eosio.token.abi
uuoskit-1.0.4.dist-info/LICENSE
uuoskit-1.0.4.dist-info/METADATA
uuoskit-1.0.4.dist-info/WHEEL
uuoskit-1.0.4.dist-info/top_level.txt
uuoskit-1.0.4.dist-info/RECORD
