Metadata-Version: 2.1
Name: uuoskit
Version: 1.0.4
Summary: Python Toolkit for EOSIO
Home-page: https://github.com/uuosio/uuoskit
Author: The UUOSIO Team
License: MIT
Platform: UNKNOWN
